napari_omero_downloader_cci/__init__.py
napari_omero_downloader_cci/_version.py
napari_omero_downloader_cci/_widget.py
napari_omero_downloader_cci/gui.py
napari_omero_downloader_cci/napari.yaml
napari_omero_downloader_cci/omero_connection.py
napari_omero_downloader_cci/omero_downloader_widget.py
napari_omero_downloader_cci/_tests/__init__.py
napari_omero_downloader_cci/_tests/conftest.py
napari_omero_downloader_cci/_tests/test_dask_loader.py
napari_omero_downloader_cci/_tests/test_tree_population.py
napari_omero_downloader_cci/_tests/test_widget.py
napari_omero_downloader_cci/_tests/test_widget_display.py
napari_omero_downloader_cci-0.3.2.dist-info/licenses/LICENSE
napari_omero_downloader_cci-0.3.2.dist-info/METADATA
napari_omero_downloader_cci-0.3.2.dist-info/WHEEL
napari_omero_downloader_cci-0.3.2.dist-info/entry_points.txt
napari_omero_downloader_cci-0.3.2.dist-info/top_level.txt
napari_omero_downloader_cci-0.3.2.dist-info/RECORD
