Metadata-Version: 2.4
Name: napari-omero-downloader-cci
Version: 0.3.2
Summary: A plugin that allows napari to connect to the Omero CCI server to visualize and download image data
Author: Simon Leclerc
Author-email: simon.leclerc@gu.se
License: 
Project-URL: Bug Tracker, https://github.com/CCI-GU-Sweden/napari-omero-downloader-cci/issues
Project-URL: Documentation, https://github.com/CCI-GU-Sweden/napari-omero-downloader-cci#README.md
Project-URL: Source Code, https://github.com/CCI-GU-Sweden/napari-omero-downloader-cci
Project-URL: User Support, https://github.com/CCI-GU-Sweden/napari-omero-downloader-cci/issues
Classifier: Development Status :: 2 - Pre-Alpha
Classifier: Framework :: napari
Classifier: Intended Audience :: Developers
Classifier: License :: OSI Approved :: MIT License
Classifier: Operating System :: OS Independent
Classifier: Programming Language :: Python
Classifier: Programming Language :: Python :: 3
Classifier: Programming Language :: Python :: 3 :: Only
Classifier: Programming Language :: Python :: 3.9
Classifier: Topic :: Scientific/Engineering :: Image Processing
Requires-Python: >=3.9
License-File: LICENSE
Requires-Dist: numpy
Requires-Dist: magicgui
Requires-Dist: qtpy
Requires-Dist: scikit-image
Requires-Dist: dask
Provides-Extra: all
Requires-Dist: napari[all]; extra == "all"
Dynamic: license-file
